Workbook

Sheet Instructions
A1: Invoice + Client & Payment Tracker (Lite)
A3: 1. 'Settings': your business name, address, tax rate and payment terms (yellow cells).
A4: 2. 'Clients': one row per client with a unique Client ID.
A5: 3. 'Invoices': one row per invoice line summary - number, client ID (dropdown), dates, subtotal. Tax, total, paid, balance, status compute automatically.
A6: 4. 'Payments': log each payment received against an invoice number. Partial payments supported.
A7: 5. 'Invoice': type an invoice number in yellow cell to generate a printable invoice.
A8: Lite: up to 25 invoices, no Summary/charts, no aging. Full version adds summary dashboard, aging buckets, charts, 500 rows.
A9: Status: Paid / Partial / Overdue (past due date with balance) / Open. 'Today' is taken from the computer clock.
A10: Created with AI assistance and reviewed by a human. Not tax or legal advice - check local invoicing rules.

Sheet Settings
A1: Business name | B1: Your Business LLC
A2: Address | B2: 123 Main St, City
A3: Email | B3: you@example.com
A4: Tax rate | B4: 0.08
A5: Payment terms (days) | B5: 30
A6: Currency symbol | B6: $

Sheet Clients
A1: Client ID | B1: Name | C1: Email | D1: Address | E1: Invoiced | F1: Paid | G1: Balance
A2: C001 | B2: Acme Design Co | C2: ap@acme.example | D2: Sample address | E2: =IF(A2="","",SUMIFS(Invoices!$G$2:$G$26,Invoices!$B$2:$B$26,A2)) | F2: =IF(A2="","",SUMIFS(Invoices!$H$2:$H$26,Invoices!$B$2:$B$26,A2)) | G2: =IF(A2="","",E2-F2)
A3: C002 | B3: Blue River Cafe | C3: owner@blueriver.example | D3: Sample address | E3: =IF(A3="","",SUMIFS(Invoices!$G$2:$G$26,Invoices!$B$2:$B$26,A3)) | F3: =IF(A3="","",SUMIFS(Invoices!$H$2:$H$26,Invoices!$B$2:$B$26,A3)) | G3: =IF(A3="","",E3-F3)
A4: C003 | B4: Northwind Studio | C4: billing@northwind.example | D4: Sample address | E4: =IF(A4="","",SUMIFS(Invoices!$G$2:$G$26,Invoices!$B$2:$B$26,A4)) | F4: =IF(A4="","",SUMIFS(Invoices!$H$2:$H$26,Invoices!$B$2:$B$26,A4)) | G4: =IF(A4="","",E4-F4)
A5: C004 | B5: Sunrise Dental | C5: office@sunrise.example | D5: Sample address | E5: =IF(A5="","",SUMIFS(Invoices!$G$2:$G$26,Invoices!$B$2:$B$26,A5)) | F5: =IF(A5="","",SUMIFS(Invoices!$H$2:$H$26,Invoices!$B$2:$B$26,A5)) | G5: =IF(A5="","",E5-F5)
E6: =IF(A6="","",SUMIFS(Invoices!$G$2:$G$26,Invoices!$B$2:$B$26,A6)) | F6: =IF(A6="","",SUMIFS(Invoices!$H$2:$H$26,Invoices!$B$2:$B$26,A6)) | G6: =IF(A6="","",E6-F6)
E7: =IF(A7="","",SUMIFS(Invoices!$G$2:$G$26,Invoices!$B$2:$B$26,A7)) | F7: =IF(A7="","",SUMIFS(Invoices!$H$2:$H$26,Invoices!$B$2:$B$26,A7)) | G7: =IF(A7="","",E7-F7)
E8: =IF(A8="","",SUMIFS(Invoices!$G$2:$G$26,Invoices!$B$2:$B$26,A8)) | F8: =IF(A8="","",SUMIFS(Invoices!$H$2:$H$26,Invoices!$B$2:$B$26,A8)) | G8: =IF(A8="","",E8-F8)
E9: =IF(A9="","",SUMIFS(Invoices!$G$2:$G$26,Invoices!$B$2:$B$26,A9)) | F9: =IF(A9="","",SUMIFS(Invoices!$H$2:$H$26,Invoices!$B$2:$B$26,A9)) | G9: =IF(A9="","",E9-F9)
E10: =IF(A10="","",SUMIFS(Invoices!$G$2:$G$26,Invoices!$B$2:$B$26,A10)) | F10: =IF(A10="","",SUMIFS(Invoices!$H$2:$H$26,Invoices!$B$2:$B$26,A10)) | G10: =IF(A10="","",E10-F10)
E11: =IF(A11="","",SUMIFS(Invoices!$G$2:$G$26,Invoices!$B$2:$B$26,A11)) | F11: =IF(A11="","",SUMIFS(Invoices!$H$2:$H$26,Invoices!$B$2:$B$26,A11)) | G11: =IF(A11="","",E11-F11)
E12: =IF(A12="","",SUMIFS(Invoices!$G$2:$G$26,Invoices!$B$2:$B$26,A12)) | F12: =IF(A12="","",SUMIFS(Invoices!$H$2:$H$26,Invoices!$B$2:$B$26,A12)) | G12: =IF(A12="","",E12-F12)
E13: =IF(A13="","",SUMIFS(Invoices!$G$2:$G$26,Invoices!$B$2:$B$26,A13)) | F13: =IF(A13="","",SUMIFS(Invoices!$H$2:$H$26,Invoices!$B$2:$B$26,A13)) | G13: =IF(A13="","",E13-F13)
E14: =IF(A14="","",SUMIFS(Invoices!$G$2:$G$26,Invoices!$B$2:$B$26,A14)) | F14: =IF(A14="","",SUMIFS(Invoices!$H$2:$H$26,Invoices!$B$2:$B$26,A14)) | G14: =IF(A14="","",E14-F14)
E15: =IF(A15="","",SUMIFS(Invoices!$G$2:$G$26,Invoices!$B$2:$B$26,A15)) | F15: =IF(A15="","",SUMIFS(Invoices!$H$2:$H$26,Invoices!$B$2:$B$26,A15)) | G15: =IF(A15="","",E15-F15)
E16: =IF(A16="","",SUMIFS(Invoices!$G$2:$G$26,Invoices!$B$2:$B$26,A16)) | F16: =IF(A16="","",SUMIFS(Invoices!$H$2:$H$26,Invoices!$B$2:$B$26,A16)) | G16: =IF(A16="","",E16-F16)
E17: =IF(A17="","",SUMIFS(Invoices!$G$2:$G$26,Invoices!$B$2:$B$26,A17)) | F17: =IF(A17="","",SUMIFS(Invoices!$H$2:$H$26,Invoices!$B$2:$B$26,A17)) | G17: =IF(A17="","",E17-F17)
... E51: =IF(A51="","",SUMIFS(Invoices!$G$2:$G$26,Invoices!$B$2:$B$26,A51)) | F51: =IF(A51="","",SUMIFS(Invoices!$H$2:$H$26,Invoices!$B$2:$B$26,A51)) | G51: =IF(A51="","",E51-F51)

Sheet Invoices
A1: Invoice # | B1: Client ID | C1: Client name | D1: Issue date | E1: Due date | F1: Subtotal | G1: Total (incl. tax) | H1: Paid | I1: Balance | J1: Status | K1: Description
A2: INV-1001 | B2: C001 | C2: =IF(B2="","",IFERROR(INDEX(Clients!$B$2:$B$51,MATCH(B2,Clients!$A$2:$A$51,0)),"?")) | D2: 46206 | E2: =IF(D2="","",D2+Settings!$B$5) | F2: 1200 | G2: =IF(F2="","",ROUND(F2*(1+Settings!$B$4),2)) | H2: =IF(A2="","",SUMIFS(Payments!$C:$C,Payments!$B:$B,A2)) | I2: =IF(A2="","",G2-H2) | J2: =IF(A2="","",IF(I2<=0,"Paid",IF(TODAY()>E2,"Overdue",IF(H2>0,"Partial","Open")))) | K2: Logo package
A3: INV-1002 | B3: C002 | C3: =IF(B3="","",IFERROR(INDEX(Clients!$B$2:$B$51,MATCH(B3,Clients!$A$2:$A$51,0)),"?")) | D3: 46223 | E3: =IF(D3="","",D3+Settings!$B$5) | F3: 450 | G3: =IF(F3="","",ROUND(F3*(1+Settings!$B$4),2)) | H3: =IF(A3="","",SUMIFS(Payments!$C:$C,Payments!$B:$B,A3)) | I3: =IF(A3="","",G3-H3) | J3: =IF(A3="","",IF(I3<=0,"Paid",IF(TODAY()>E3,"Overdue",IF(H3>0,"Partial","Open")))) | K3: Menu design
A4: INV-1003 | B4: C003 | C4: =IF(B4="","",IFERROR(INDEX(Clients!$B$2:$B$51,MATCH(B4,Clients!$A$2:$A$51,0)),"?")) | D4: 46239 | E4: =IF(D4="","",D4+Settings!$B$5) | F4: 2300 | G4: =IF(F4="","",ROUND(F4*(1+Settings!$B$4),2)) | H4: =IF(A4="","",SUMIFS(Payments!$C:$C,Payments!$B:$B,A4)) | I4: =IF(A4="","",G4-H4) | J4: =IF(A4="","",IF(I4<=0,"Paid",IF(TODAY()>E4,"Overdue",IF(H4>0,"Partial","Open")))) | K4: Website pages
A5: INV-1004 | B5: C001 | C5: =IF(B5="","",IFERROR(INDEX(Clients!$B$2:$B$51,MATCH(B5,Clients!$A$2:$A$51,0)),"?")) | D5: 46262 | E5: =IF(D5="","",D5+Settings!$B$5) | F5: 800 | G5: =IF(F5="","",ROUND(F5*(1+Settings!$B$4),2)) | H5: =IF(A5="","",SUMIFS(Payments!$C:$C,Payments!$B:$B,A5)) | I5: =IF(A5="","",G5-H5) | J5: =IF(A5="","",IF(I5<=0,"Paid",IF(TODAY()>E5,"Overdue",IF(H5>0,"Partial","Open")))) | K5: Brand guide
A6: INV-1005 | B6: C004 | C6: =IF(B6="","",IFERROR(INDEX(Clients!$B$2:$B$51,MATCH(B6,Clients!$A$2:$A$51,0)),"?")) | D6: 46275 | E6: =IF(D6="","",D6+Settings!$B$5) | F6: 650 | G6: =IF(F6="","",ROUND(F6*(1+Settings!$B$4),2)) | H6: =IF(A6="","",SUMIFS(Payments!$C:$C,Payments!$B:$B,A6)) | I6: =IF(A6="","",G6-H6) | J6: =IF(A6="","",IF(I6<=0,"Paid",IF(TODAY()>E6,"Overdue",IF(H6>0,"Partial","Open")))) | K6: Flyers
A7: INV-1006 | B7: C003 | C7: =IF(B7="","",IFERROR(INDEX(Clients!$B$2:$B$51,MATCH(B7,Clients!$A$2:$A$51,0)),"?")) | D7: 46296 | E7: =IF(D7="","",D7+Settings!$B$5) | F7: 1500 | G7: =IF(F7="","",ROUND(F7*(1+Settings!$B$4),2)) | H7: =IF(A7="","",SUMIFS(Payments!$C:$C,Payments!$B:$B,A7)) | I7: =IF(A7="","",G7-H7) | J7: =IF(A7="","",IF(I7<=0,"Paid",IF(TODAY()>E7,"Overdue",IF(H7>0,"Partial","Open")))) | K7: Retainer Oct
C8: =IF(B8="","",IFERROR(INDEX(Clients!$B$2:$B$51,MATCH(B8,Clients!$A$2:$A$51,0)),"?")) | E8: =IF(D8="","",D8+Settings!$B$5) | G8: =IF(F8="","",ROUND(F8*(1+Settings!$B$4),2)) | H8: =IF(A8="","",SUMIFS(Payments!$C:$C,Payments!$B:$B,A8)) | I8: =IF(A8="","",G8-H8) | J8: =IF(A8="","",IF(I8<=0,"Paid",IF(TODAY()>E8,"Overdue",IF(H8>0,"Partial","Open"))))
C9: =IF(B9="","",IFERROR(INDEX(Clients!$B$2:$B$51,MATCH(B9,Clients!$A$2:$A$51,0)),"?")) | E9: =IF(D9="","",D9+Settings!$B$5) | G9: =IF(F9="","",ROUND(F9*(1+Settings!$B$4),2)) | H9: =IF(A9="","",SUMIFS(Payments!$C:$C,Payments!$B:$B,A9)) | I9: =IF(A9="","",G9-H9) | J9: =IF(A9="","",IF(I9<=0,"Paid",IF(TODAY()>E9,"Overdue",IF(H9>0,"Partial","Open"))))
C10: =IF(B10="","",IFERROR(INDEX(Clients!$B$2:$B$51,MATCH(B10,Clients!$A$2:$A$51,0)),"?")) | E10: =IF(D10="","",D10+Settings!$B$5) | G10: =IF(F10="","",ROUND(F10*(1+Settings!$B$4),2)) | H10: =IF(A10="","",SUMIFS(Payments!$C:$C,Payments!$B:$B,A10)) | I10: =IF(A10="","",G10-H10) | J10: =IF(A10="","",IF(I10<=0,"Paid",IF(TODAY()>E10,"Overdue",IF(H10>0,"Partial","Open"))))
C11: =IF(B11="","",IFERROR(INDEX(Clients!$B$2:$B$51,MATCH(B11,Clients!$A$2:$A$51,0)),"?")) | E11: =IF(D11="","",D11+Settings!$B$5) | G11: =IF(F11="","",ROUND(F11*(1+Settings!$B$4),2)) | H11: =IF(A11="","",SUMIFS(Payments!$C:$C,Payments!$B:$B,A11)) | I11: =IF(A11="","",G11-H11) | J11: =IF(A11="","",IF(I11<=0,"Paid",IF(TODAY()>E11,"Overdue",IF(H11>0,"Partial","Open"))))
C12: =IF(B12="","",IFERROR(INDEX(Clients!$B$2:$B$51,MATCH(B12,Clients!$A$2:$A$51,0)),"?")) | E12: =IF(D12="","",D12+Settings!$B$5) | G12: =IF(F12="","",ROUND(F12*(1+Settings!$B$4),2)) | H12: =IF(A12="","",SUMIFS(Payments!$C:$C,Payments!$B:$B,A12)) | I12: =IF(A12="","",G12-H12) | J12: =IF(A12="","",IF(I12<=0,"Paid",IF(TODAY()>E12,"Overdue",IF(H12>0,"Partial","Open"))))
C13: =IF(B13="","",IFERROR(INDEX(Clients!$B$2:$B$51,MATCH(B13,Clients!$A$2:$A$51,0)),"?")) | E13: =IF(D13="","",D13+Settings!$B$5) | G13: =IF(F13="","",ROUND(F13*(1+Settings!$B$4),2)) | H13: =IF(A13="","",SUMIFS(Payments!$C:$C,Payments!$B:$B,A13)) | I13: =IF(A13="","",G13-H13) | J13: =IF(A13="","",IF(I13<=0,"Paid",IF(TODAY()>E13,"Overdue",IF(H13>0,"Partial","Open"))))
C14: =IF(B14="","",IFERROR(INDEX(Clients!$B$2:$B$51,MATCH(B14,Clients!$A$2:$A$51,0)),"?")) | E14: =IF(D14="","",D14+Settings!$B$5) | G14: =IF(F14="","",ROUND(F14*(1+Settings!$B$4),2)) | H14: =IF(A14="","",SUMIFS(Payments!$C:$C,Payments!$B:$B,A14)) | I14: =IF(A14="","",G14-H14) | J14: =IF(A14="","",IF(I14<=0,"Paid",IF(TODAY()>E14,"Overdue",IF(H14>0,"Partial","Open"))))
C15: =IF(B15="","",IFERROR(INDEX(Clients!$B$2:$B$51,MATCH(B15,Clients!$A$2:$A$51,0)),"?")) | E15: =IF(D15="","",D15+Settings!$B$5) | G15: =IF(F15="","",ROUND(F15*(1+Settings!$B$4),2)) | H15: =IF(A15="","",SUMIFS(Payments!$C:$C,Payments!$B:$B,A15)) | I15: =IF(A15="","",G15-H15) | J15: =IF(A15="","",IF(I15<=0,"Paid",IF(TODAY()>E15,"Overdue",IF(H15>0,"Partial","Open"))))
C16: =IF(B16="","",IFERROR(INDEX(Clients!$B$2:$B$51,MATCH(B16,Clients!$A$2:$A$51,0)),"?")) | E16: =IF(D16="","",D16+Settings!$B$5) | G16: =IF(F16="","",ROUND(F16*(1+Settings!$B$4),2)) | H16: =IF(A16="","",SUMIFS(Payments!$C:$C,Payments!$B:$B,A16)) | I16: =IF(A16="","",G16-H16) | J16: =IF(A16="","",IF(I16<=0,"Paid",IF(TODAY()>E16,"Overdue",IF(H16>0,"Partial","Open"))))
C17: =IF(B17="","",IFERROR(INDEX(Clients!$B$2:$B$51,MATCH(B17,Clients!$A$2:$A$51,0)),"?")) | E17: =IF(D17="","",D17+Settings!$B$5) | G17: =IF(F17="","",ROUND(F17*(1+Settings!$B$4),2)) | H17: =IF(A17="","",SUMIFS(Payments!$C:$C,Payments!$B:$B,A17)) | I17: =IF(A17="","",G17-H17) | J17: =IF(A17="","",IF(I17<=0,"Paid",IF(TODAY()>E17,"Overdue",IF(H17>0,"Partial","Open"))))
C18: =IF(B18="","",IFERROR(INDEX(Clients!$B$2:$B$51,MATCH(B18,Clients!$A$2:$A$51,0)),"?")) | E18: =IF(D18="","",D18+Settings!$B$5) | G18: =IF(F18="","",ROUND(F18*(1+Settings!$B$4),2)) | H18: =IF(A18="","",SUMIFS(Payments!$C:$C,Payments!$B:$B,A18)) | I18: =IF(A18="","",G18-H18) | J18: =IF(A18="","",IF(I18<=0,"Paid",IF(TODAY()>E18,"Overdue",IF(H18>0,"Partial","Open"))))
C19: =IF(B19="","",IFERROR(INDEX(Clients!$B$2:$B$51,MATCH(B19,Clients!$A$2:$A$51,0)),"?")) | E19: =IF(D19="","",D19+Settings!$B$5) | G19: =IF(F19="","",ROUND(F19*(1+Settings!$B$4),2)) | H19: =IF(A19="","",SUMIFS(Payments!$C:$C,Payments!$B:$B,A19)) | I19: =IF(A19="","",G19-H19) | J19: =IF(A19="","",IF(I19<=0,"Paid",IF(TODAY()>E19,"Overdue",IF(H19>0,"Partial","Open"))))
... C26: =IF(B26="","",IFERROR(INDEX(Clients!$B$2:$B$51,MATCH(B26,Clients!$A$2:$A$51,0)),"?")) | E26: =IF(D26="","",D26+Settings!$B$5) | G26: =IF(F26="","",ROUND(F26*(1+Settings!$B$4),2)) | H26: =IF(A26="","",SUMIFS(Payments!$C:$C,Payments!$B:$B,A26)) | I26: =IF(A26="","",G26-H26) | J26: =IF(A26="","",IF(I26<=0,"Paid",IF(TODAY()>E26,"Overdue",IF(H26>0,"Partial","Open"))))

Sheet Payments
A1: Date | B1: Invoice # | C1: Amount | D1: Method | E1: Note
A2: 46228 | B2: INV-1001 | C2: 1296 | D2: Bank
A3: 46264 | B3: INV-1002 | C3: 200 | D3: Card
A4: 46267 | B4: INV-1003 | C4: 2484 | D4: Bank
A5: 46300 | B5: INV-1005 | C5: 702 | D5: PayPal

Sheet Invoice
A1: =Settings!B1 | E1: INVOICE
A2: =Settings!B2
A3: =Settings!B3 | D3: Invoice # | E3: INV-1003
D4: Issue date | E4: =IFERROR(INDEX(Invoices!$D$2:$D$26,MATCH($E$3,Invoices!$A$2:$A$26,0)),"")
D5: Due date | E5: =IFERROR(INDEX(Invoices!$E$2:$E$26,MATCH($E$3,Invoices!$A$2:$A$26,0)),"")
A6: Bill to:
A7: =IFERROR(INDEX(Invoices!$C$2:$C$26,MATCH($E$3,Invoices!$A$2:$A$26,0)),"")
A9: Description | E9: Amount
A10: =IFERROR(INDEX(Invoices!$K$2:$K$26,MATCH($E$3,Invoices!$A$2:$A$26,0)),"") | E10: =IFERROR(INDEX(Invoices!$F$2:$F$26,MATCH($E$3,Invoices!$A$2:$A$26,0)),"")
D12: Subtotal | E12: =E10
D13: Tax | E13: =IFERROR(E14-E12,0)
D14: Total | E14: =IFERROR(INDEX(Invoices!$G$2:$G$26,MATCH($E$3,Invoices!$A$2:$A$26,0)),"")
D15: Paid | E15: =IFERROR(INDEX(Invoices!$H$2:$H$26,MATCH($E$3,Invoices!$A$2:$A$26,0)),"")
D16: Balance due | E16: =IFERROR(INDEX(Invoices!$I$2:$I$26,MATCH($E$3,Invoices!$A$2:$A$26,0)),"")
A18: ="Payment due within "&Settings!B5&" days. Thank you!"
